pykraken/__init__.py
pykraken/client.py
pykraken/config.py
pykraken/convert.py
pykraken/exceptions.py
pykraken/kprivate.py
pykraken/kpublic.py
pykraken/pykraken.py
pykraken-0.1.0.dist-info/top_level.txt
pykraken-0.1.0.dist-info/METADATA
pykraken-0.1.0.dist-info/DESCRIPTION.rst
pykraken-0.1.0.dist-info/metadata.json
pykraken-0.1.0.dist-info/WHEEL
pykraken-0.1.0.dist-info/RECORD
