Metadata-Version: 1.1
Name: pykraken
Version: 0.1.0
Summary: python implementation of https://www.kraken.com/ API
Home-page: https://github.com/euri10/pykraken
Author: Benoit Barthelet
Author-email: benoit.barthelet@gmail.com
License: ISCL
Keywords: pykraken
Platform: UNKNOWN
Classifier: Development Status :: 2 - Pre-Alpha
Classifier: Intended Audience :: Developers
Classifier: License :: OSI Approved :: ISC License (ISCL)
Classifier: Natural Language :: English
Classifier: Programming Language :: Python :: 2
Classifier: Programming Language :: Python :: 2.6
Classifier: Programming Language :: Python :: 2.7
Classifier: Programming Language :: Python :: 3
Classifier: Programming Language :: Python :: 3.3
Classifier: Programming Language :: Python :: 3.4
Classifier: Programming Language :: Python :: 3.5
